aiodrive-4.0.dist-info/METADATA
aiodrive-4.0.dist-info/WHEEL
aiodrive-4.0.dist-info/RECORD
aiodrive/__init__.py
aiodrive/internal/future.py
aiodrive/internal/queue.py
aiodrive/internal/sized.py
aiodrive/modules/__init__.py
aiodrive/modules/aiter.py
aiodrive/modules/amass.py
aiodrive/modules/awaitable.py
aiodrive/modules/bivalent_context_manager.py
aiodrive/modules/button.py
aiodrive/modules/cancel.py
aiodrive/modules/checkpoint.py
aiodrive/modules/cleanup.py
aiodrive/modules/closing.py
aiodrive/modules/concurrent_contexts.py
aiodrive/modules/contextualize.py
aiodrive/modules/daemon.py
aiodrive/modules/event_loop.py
aiodrive/modules/future_state.py
aiodrive/modules/gather.py
aiodrive/modules/guaranteed_task.py
aiodrive/modules/handle.py
aiodrive/modules/io.py
aiodrive/modules/kqueue.py
aiodrive/modules/latch.py
aiodrive/modules/map.py
aiodrive/modules/multiprocessing.py
aiodrive/modules/nestable_lock.py
aiodrive/modules/prime.py
aiodrive/modules/process.py
aiodrive/modules/race.py
aiodrive/modules/repeat.py
aiodrive/modules/run.py
aiodrive/modules/scope.py
aiodrive/modules/shield.py
aiodrive/modules/signals.py
aiodrive/modules/task_group.py
aiodrive/modules/tcp.py
aiodrive/modules/thread_loop.py
aiodrive/modules/thread_manager.py
aiodrive/modules/thread_safe_lock.py
aiodrive/modules/thread_safe_state.py
aiodrive/modules/thread_sync.py
aiodrive/modules/watch.py
aiodrive/modules/zip.py
