Metadata-Version: 2.4
Name: aiodrive
Version: 4.0
Requires-Python: ~=3.12
Summary: Collection of utilities for working with asynchronous Python code
License-Expression: EUPL-1.2
Project-URL: Repository, https://github.com/slietar/aiodrive
